gerapy_proxy/__init__.py
gerapy_proxy/__version__.py
gerapy_proxy/exceptions.py
gerapy_proxy/middlewares.py
gerapy_proxy/settings.py
gerapy_proxy/utils.py
gerapy_proxy-0.0.3.dist-info/METADATA
gerapy_proxy-0.0.3.dist-info/WHEEL
gerapy_proxy-0.0.3.dist-info/top_level.txt
gerapy_proxy-0.0.3.dist-info/RECORD
